cgdat/__init__.py
cgdat/cgdat_gui.py
cgdat/create_shortcut_cl.py
cgdat/start_cl.py
cgdat/qt_custom/__init__.py
cgdat/qt_custom/qt_dialogs.py
cgdat/qt_custom/qt_extra.py
cgdat/qt_custom/qt_thread.py
cgdat/qt_ui/__init__.py
cgdat/qt_ui/about_ui.py
cgdat/qt_ui/cgdat_ui.py
cgdat/qt_ui/import_dialog_ui.py
cgdat/qt_ui/output_settings_ui.py
cgdat/qt_ui/progress_dialog_ui.py
cgdat/qt_ui/splash_screen_ui.py
cgdat/static/config/settings_save.ini
cgdat/static/css/style.css
cgdat/static/docs/_build/doctrees/code.doctree
cgdat/static/docs/_build/doctrees/environment.pickle
cgdat/static/docs/_build/doctrees/index.doctree
cgdat/static/docs/_build/doctrees/info.doctree
cgdat/static/docs/_build/doctrees/installation.doctree
cgdat/static/docs/_build/doctrees/use.doctree
cgdat/static/docs/_build/doctrees/_auto_rst/cgdat.doctree
cgdat/static/docs/_build/doctrees/_auto_rst/cgdat.qt_custom.doctree
cgdat/static/docs/_build/doctrees/_auto_rst/cgdat.qt_ui.doctree
cgdat/static/docs/_build/doctrees/_auto_rst/create_cgdat_shortcut.doctree
cgdat/static/docs/_build/doctrees/_auto_rst/install_cgdat.doctree
cgdat/static/docs/_build/doctrees/_auto_rst/modules.doctree
cgdat/static/docs/_build/doctrees/_auto_rst/start_cgdat.doctree
cgdat/static/docs/_build/doctrees/_auto_rst/_autosummary/cgdat.qt_custom.qt_dialogs.doctree
cgdat/static/docs/_build/doctrees/_auto_rst/_autosummary/cgdat.qt_custom.qt_extra.doctree
cgdat/static/docs/_build/doctrees/_auto_rst/_autosummary/cgdat.qt_custom.qt_thread.doctree
cgdat/static/docs/_build/doctrees/_autosummary/cgdat.cgdat_gui.doctree
cgdat/static/docs/_build/doctrees/_autosummary/cgdat.create_shortcut_cl.doctree
cgdat/static/docs/_build/doctrees/_autosummary/cgdat.qt_custom.doctree
cgdat/static/docs/_build/doctrees/_autosummary/cgdat.qt_ui.doctree
cgdat/static/docs/_build/doctrees/_autosummary/cgdat.start_cl.doctree
cgdat/static/docs/_build/doctrees/_autosummary/create_cgdat_shortcut.doctree
cgdat/static/docs/_build/doctrees/_autosummary/install_cgdat.doctree
cgdat-2.4.2.dist-info/LICENSE
cgdat-2.4.2.dist-info/METADATA
cgdat-2.4.2.dist-info/WHEEL
cgdat-2.4.2.dist-info/entry_points.txt
cgdat-2.4.2.dist-info/top_level.txt
cgdat-2.4.2.dist-info/RECORD
