Metadata-Version: 2.1
Name: cgdat
Version: 2.4.2
Summary: A simple csv data analyse tool.
Home-page: https://github.com/rickstaa/CGDAT
Author: Rick Staa
Author-email: rick.staa@outlook.com
License: UNKNOWN
Download-URL: https://github.com/rickstaa/CGDAT/archive/v2.4.2.tar.gz
Platform: UNKNOWN
Classifier: Programming Language :: Python :: 3
Classifier: License :: OSI Approved :: MIT License
Classifier: Operating System :: OS Independent
Requires-Dist: pyqt5
Requires-Dist: pandas
Requires-Dist: numpy
Requires-Dist: xlsxwriter
Requires-Dist: winshell
Requires-Dist: pywin32
Requires-Dist: configobj
Provides-Extra: dev
Requires-Dist: bumpversion ; extra == 'dev'
Requires-Dist: pylint ; extra == 'dev'
Provides-Extra: docs
Requires-Dist: sphinx ; extra == 'docs'
Requires-Dist: sphinxcontrib-napoleon ; extra == 'docs'
Requires-Dist: sphinx-rtd-theme ; extra == 'docs'
Requires-Dist: sphinx-navtree ; extra == 'docs'
Requires-Dist: sphinx-autobuild ; extra == 'docs'
Requires-Dist: sphinxcontrib.yt ; extra == 'docs'
Requires-Dist: docutils ; extra == 'docs'
Requires-Dist: doc8 ; extra == 'docs'
